yahoo_search_test/__init__.py
yahoo_search_test/api_client.py
yahoo_search_test/configuration.py
yahoo_search_test/exceptions.py
yahoo_search_test/rest.py
yahoo_search_test/api/__init__.py
yahoo_search_test/api/account_customizer_service_api.py
yahoo_search_test/api/account_link_service_api.py
yahoo_search_test/api/account_management_service_api.py
yahoo_search_test/api/account_service_api.py
yahoo_search_test/api/account_shared_service_api.py
yahoo_search_test/api/account_tracking_url_service_api.py
yahoo_search_test/api/ad_group_ad_label_service_api.py
yahoo_search_test/api/ad_group_ad_service_api.py
yahoo_search_test/api/ad_group_asset_service_api.py
yahoo_search_test/api/ad_group_bid_multiplier_service_api.py
yahoo_search_test/api/ad_group_criterion_customizer_service_api.py
yahoo_search_test/api/ad_group_criterion_label_service_api.py
yahoo_search_test/api/ad_group_criterion_service_api.py
yahoo_search_test/api/ad_group_customizer_service_api.py
yahoo_search_test/api/ad_group_label_service_api.py
yahoo_search_test/api/ad_group_retargeting_list_service_api.py
yahoo_search_test/api/ad_group_service_api.py
yahoo_search_test/api/ad_group_webpage_service_api.py
yahoo_search_test/api/app_link_service_api.py
yahoo_search_test/api/asset_service_api.py
yahoo_search_test/api/audit_log_service_api.py
yahoo_search_test/api/balance_service_api.py
yahoo_search_test/api/base_account_service_api.py
yahoo_search_test/api/bidding_seasonality_adjustment_service_api.py
yahoo_search_test/api/bidding_strategy_service_api.py
yahoo_search_test/api/budget_order_service_api.py
yahoo_search_test/api/campaign_asset_service_api.py
yahoo_search_test/api/campaign_budget_service_api.py
yahoo_search_test/api/campaign_criterion_service_api.py
yahoo_search_test/api/campaign_customizer_service_api.py
yahoo_search_test/api/campaign_export_service_api.py
yahoo_search_test/api/campaign_label_service_api.py
yahoo_search_test/api/campaign_retargeting_list_service_api.py
yahoo_search_test-1.0.1.dist-info/METADATA
yahoo_search_test-1.0.1.dist-info/WHEEL
yahoo_search_test-1.0.1.dist-info/top_level.txt
yahoo_search_test-1.0.1.dist-info/RECORD
